setup.py
caoliu/__init__.py
caoliu/__init__.pyc
caoliu.egg-info/PKG-INFO
caoliu.egg-info/SOURCES.txt
caoliu.egg-info/dependency_links.txt
caoliu.egg-info/entry_points.txt
caoliu.egg-info/top_level.txt