Metadata-Version: 1.0
Name: caoliu
Version: 0.0.5
Summary: 这个真的不是邀请码
Home-page: http://github.com/tianyu0915/caoliu
Author: TY
Author-email: tianyu0915@gmail.com
License: UNKNOWN
Platform: UNKNOWN
